examples/__init__.py
examples/basic_message.py
examples/basic_message_without_hostname.py
examples/complete_error_traceback.py
examples/error_message.py
examples/success_message.py
slack_logger/__init__.py
slack_logger/message_logger.py
slack_logger/utils.py
python_slack_logger-0.10.1.dist-info/LICENSE
python_slack_logger-0.10.1.dist-info/METADATA
python_slack_logger-0.10.1.dist-info/WHEEL
python_slack_logger-0.10.1.dist-info/top_level.txt
python_slack_logger-0.10.1.dist-info/RECORD
