Metadata-Version: 2.1
Name: python-slack-logger
Version: 0.10.1
Summary: Slack Logger is a custom message logger to Slack for Python 3
Home-page: https://github.com/chinnichaitanya/python-slack-logger
Author: Chaitanya Chinni
License: MIT License
Keywords: monitoring,slack,messaging,logging,health-check,notification-service,notification,slack-api
Platform: UNKNOWN
Classifier: Environment :: Web Environment
Classifier: Intended Audience :: Developers
Classifier: License :: OSI Approved :: MIT License
Classifier: Operating System :: OS Independent
Classifier: Programming Language :: Python :: 3
Classifier: Topic :: Internet :: WWW/HTTP
Classifier: Topic :: Internet :: WWW/HTTP :: Dynamic Content
Requires-Python: >=3.6
License-File: LICENSE
Requires-Dist: slackclient (==2.9.4)
Requires-Dist: pyyaml (==6.0.1)
